{
  "last_run": "2026-05-22T01:28:12Z",
  "last_run_id": "26263009189",
  "monthly_summary_issue": 189,
  "comments_made": {
    "80": "2026-04-16",
    "83": "2026-04-16",
    "88": "2026-04-16",
    "126": "2026-04-19",
    "154_pr": "2026-04-27"
  },
  "open_repo_assist_prs": [],
  "open_repo_assist_issues": [
    {"number": 188, "title": "ci: add --locked flag (bundle, push failed)"},
    {"number": 192, "title": "test: add unit tests for theme.rs (duplicate, safe to close)"}
  ],
  "backlog_cursor": {
    "issues": "no human issues open",
    "next_issue_to_process": "check for new human issues next run"
  },
  "notes": "2026-05-22 run: Tasks 2+5. Task 2: No human issues, only Repo Assist automated items. Task 5: Removed 4 redundant ensure_selection_visible() calls in handle_local_filter_input (handler.rs) - those immediately follow apply_filter() which already calls it. Bundle saved to artifact. All previous PRs (#187 #190 #191 #193 #196 #198 #199) merged/closed by maintainer."
}
